pyflaglet/__init__.py
pyflaglet/bindings.cpython-38-darwin.so
pyflaglet-1.0.0.dist-info/LICENSE.txt
pyflaglet-1.0.0.dist-info/METADATA
pyflaglet-1.0.0.dist-info/WHEEL
pyflaglet-1.0.0.dist-info/top_level.txt
pyflaglet-1.0.0.dist-info/RECORD
